pyexcel_xlsxwx/__init__.py
pyexcel_xlsxwx/app.py
pyexcel_xlsxwx/default.yaml
pyexcel_xlsxwx-0.1.8.dist-info/LICENSE
pyexcel_xlsxwx-0.1.8.dist-info/WHEEL
pyexcel_xlsxwx-0.1.8.dist-info/METADATA
pyexcel_xlsxwx-0.1.8.dist-info/RECORD
