Metadata-Version: 2.1
Name: pyexcel-xlsxwx
Version: 0.1.8
Summary: Save pyexcel data with XlsxWriter, while retaining good formatting.
Home-page: https://github.com/patarapolw/pyexcel-xlsxwx
License: MIT
Keywords: pyexcel,excel,xlsxwriter
Author: Pacharapol Withayasakpunt
Author-email: patarapolw@gmail.com
Requires-Python: >=3.7
Classifier: License :: OSI Approved :: MIT License
Classifier: Programming Language :: Python :: 3
Classifier: Programming Language :: Python :: 3.10
Classifier: Programming Language :: Python :: 3.7
Classifier: Programming Language :: Python :: 3.8
Classifier: Programming Language :: Python :: 3.9
Requires-Dist: XlsxWriter (>=3.0.2,<4.0.0)
Requires-Dist: ruamel.yaml (>=0.17.20,<0.18.0)
Project-URL: Repository, https://github.com/patarapolw/pyexcel-xlsxwx
